perumal/__init__.py
perumal-0.1.dist-info/LICENSE.txt
perumal-0.1.dist-info/METADATA
perumal-0.1.dist-info/WHEEL
perumal-0.1.dist-info/top_level.txt
perumal-0.1.dist-info/RECORD
