Metadata-Version: 2.1
Name: perumal
Version: 0.1
Summary: This is the first package for perumal
Home-page: UNKNOWN
Author: srinivasan_rd
Author-email: srinivasan.r.d@egrovesys.com
License: UNKNOWN
Platform: UNKNOWN
Classifier: Programming Language :: Python :: 3
Classifier: License :: OSI Approved :: MIT License
Classifier: Operating System :: OS Independent
